{
  "name": "single-dc-l3ls-v2",
  "type": "clab",
  "clab": {
    "config": {
      "prefix": "clab",
      "mgmt": {
        "network": "clab-mgmt-net",
        "bridge": "br-ba55097e2c0c",
        "ipv4-subnet": "172.16.100.0/24",
        "ipv4-gw": "172.16.100.1",
        "ipv6-subnet": "fd00:100:100::/64",
        "ipv6-gw": "fd00:100:100::1",
        "external-access": true
      }
    }
  },
  "ssh-pub-keys": [],
  "nodes": {
    "dc1-leaf1a": {
      "index": "0",
      "shortname": "dc1-leaf1a",
      "longname": "clab-single-dc-l3ls-v2-dc1-leaf1a",
      "fqdn": "dc1-leaf1a.single-dc-l3ls-v2.io",
      "group": "",
      "labdir": "/home/matt/labs/avd_clab/single-dc-l3ls/clab-single-dc-l3ls-v2/dc1-leaf1a",
      "kind": "arista_ceos",
      "image": "ceos:4.35.0F",
      "mgmt-net": "",
      "mgmt-intf": "Management0",
      "mgmt-ipv4-address": "172.16.100.102",
      "mgmt-ipv4-prefix-length": 24,
      "mgmt-ipv6-address": "fd00:100:100::7",
      "mgmt-ipv6-prefix-length": 64,
      "mac-address": "00:1c:73:d0:02:eb",
      "labels": {
        "clab-mgmt-net-bridge": "br-ba55097e2c0c",
        "clab-node-group": "",
        "clab-node-kind": "arista_ceos",
        "clab-node-lab-dir": "/home/matt/labs/avd_clab/single-dc-l3ls/clab-single-dc-l3ls-v2/dc1-leaf1a",
        "clab-node-longname": "clab-single-dc-l3ls-v2-dc1-leaf1a",
        "clab-node-name": "dc1-leaf1a",
        "clab-node-type": "",
        "clab-owner": "matt",
        "clab-topo-file": "/home/matt/labs/avd_clab/single-dc-l3ls/l3ls.clab.yml",
        "containerlab": "single-dc-l3ls-v2"
      },
      "port-bindings": [
      ]
    },
    "dc1-leaf1b": {
      "index": "1",
      "shortname": "dc1-leaf1b",
      "longname": "clab-single-dc-l3ls-v2-dc1-leaf1b",
      "fqdn": "dc1-leaf1b.single-dc-l3ls-v2.io",
      "group": "",
      "labdir": "/home/matt/labs/avd_clab/single-dc-l3ls/clab-single-dc-l3ls-v2/dc1-leaf1b",
      "kind": "arista_ceos",
      "image": "ceos:4.35.0F",
      "mgmt-net": "",
      "mgmt-intf": "Management0",
      "mgmt-ipv4-address": "172.16.100.103",
      "mgmt-ipv4-prefix-length": 24,
      "mgmt-ipv6-address": "fd00:100:100::6",
      "mgmt-ipv6-prefix-length": 64,
      "mac-address": "00:1c:73:9c:15:7d",
      "labels": {
        "clab-mgmt-net-bridge": "br-ba55097e2c0c",
        "clab-node-group": "",
        "clab-node-kind": "arista_ceos",
        "clab-node-lab-dir": "/home/matt/labs/avd_clab/single-dc-l3ls/clab-single-dc-l3ls-v2/dc1-leaf1b",
        "clab-node-longname": "clab-single-dc-l3ls-v2-dc1-leaf1b",
        "clab-node-name": "dc1-leaf1b",
        "clab-node-type": "",
        "clab-owner": "matt",
        "clab-topo-file": "/home/matt/labs/avd_clab/single-dc-l3ls/l3ls.clab.yml",
        "containerlab": "single-dc-l3ls-v2"
      },
      "port-bindings": [
      ]
    },
    "dc1-leaf1c": {
      "index": "2",
      "shortname": "dc1-leaf1c",
      "longname": "clab-single-dc-l3ls-v2-dc1-leaf1c",
      "fqdn": "dc1-leaf1c.single-dc-l3ls-v2.io",
      "group": "",
      "labdir": "/home/matt/labs/avd_clab/single-dc-l3ls/clab-single-dc-l3ls-v2/dc1-leaf1c",
      "kind": "arista_ceos",
      "image": "ceos:4.35.0F",
      "mgmt-net": "",
      "mgmt-intf": "Management0",
      "mgmt-ipv4-address": "172.16.100.106",
      "mgmt-ipv4-prefix-length": 24,
      "mgmt-ipv6-address": "fd00:100:100::3",
      "mgmt-ipv6-prefix-length": 64,
      "mac-address": "00:1c:73:04:92:90",
      "labels": {
        "clab-mgmt-net-bridge": "br-ba55097e2c0c",
        "clab-node-group": "",
        "clab-node-kind": "arista_ceos",
        "clab-node-lab-dir": "/home/matt/labs/avd_clab/single-dc-l3ls/clab-single-dc-l3ls-v2/dc1-leaf1c",
        "clab-node-longname": "clab-single-dc-l3ls-v2-dc1-leaf1c",
        "clab-node-name": "dc1-leaf1c",
        "clab-node-type": "",
        "clab-owner": "matt",
        "clab-topo-file": "/home/matt/labs/avd_clab/single-dc-l3ls/l3ls.clab.yml",
        "containerlab": "single-dc-l3ls-v2"
      },
      "port-bindings": [
      ]
    },
    "dc1-leaf2a": {
      "index": "3",
      "shortname": "dc1-leaf2a",
      "longname": "clab-single-dc-l3ls-v2-dc1-leaf2a",
      "fqdn": "dc1-leaf2a.single-dc-l3ls-v2.io",
      "group": "",
      "labdir": "/home/matt/labs/avd_clab/single-dc-l3ls/clab-single-dc-l3ls-v2/dc1-leaf2a",
      "kind": "arista_ceos",
      "image": "ceos:4.35.0F",
      "mgmt-net": "",
      "mgmt-intf": "Management0",
      "mgmt-ipv4-address": "172.16.100.104",
      "mgmt-ipv4-prefix-length": 24,
      "mgmt-ipv6-address": "fd00:100:100::8",
      "mgmt-ipv6-prefix-length": 64,
      "mac-address": "00:1c:73:5a:80:88",
      "labels": {
        "clab-mgmt-net-bridge": "br-ba55097e2c0c",
        "clab-node-group": "",
        "clab-node-kind": "arista_ceos",
        "clab-node-lab-dir": "/home/matt/labs/avd_clab/single-dc-l3ls/clab-single-dc-l3ls-v2/dc1-leaf2a",
        "clab-node-longname": "clab-single-dc-l3ls-v2-dc1-leaf2a",
        "clab-node-name": "dc1-leaf2a",
        "clab-node-type": "",
        "clab-owner": "matt",
        "clab-topo-file": "/home/matt/labs/avd_clab/single-dc-l3ls/l3ls.clab.yml",
        "containerlab": "single-dc-l3ls-v2"
      },
      "port-bindings": [
      ]
    },
    "dc1-leaf2b": {
      "index": "4",
      "shortname": "dc1-leaf2b",
      "longname": "clab-single-dc-l3ls-v2-dc1-leaf2b",
      "fqdn": "dc1-leaf2b.single-dc-l3ls-v2.io",
      "group": "",
      "labdir": "/home/matt/labs/avd_clab/single-dc-l3ls/clab-single-dc-l3ls-v2/dc1-leaf2b",
      "kind": "arista_ceos",
      "image": "ceos:4.35.0F",
      "mgmt-net": "",
      "mgmt-intf": "Management0",
      "mgmt-ipv4-address": "172.16.100.105",
      "mgmt-ipv4-prefix-length": 24,
      "mgmt-ipv6-address": "fd00:100:100::2",
      "mgmt-ipv6-prefix-length": 64,
      "mac-address": "00:1c:73:3f:14:f5",
      "labels": {
        "clab-mgmt-net-bridge": "br-ba55097e2c0c",
        "clab-node-group": "",
        "clab-node-kind": "arista_ceos",
        "clab-node-lab-dir": "/home/matt/labs/avd_clab/single-dc-l3ls/clab-single-dc-l3ls-v2/dc1-leaf2b",
        "clab-node-longname": "clab-single-dc-l3ls-v2-dc1-leaf2b",
        "clab-node-name": "dc1-leaf2b",
        "clab-node-type": "",
        "clab-owner": "matt",
        "clab-topo-file": "/home/matt/labs/avd_clab/single-dc-l3ls/l3ls.clab.yml",
        "containerlab": "single-dc-l3ls-v2"
      },
      "port-bindings": [
      ]
    },
    "dc1-leaf2c": {
      "index": "5",
      "shortname": "dc1-leaf2c",
      "longname": "clab-single-dc-l3ls-v2-dc1-leaf2c",
      "fqdn": "dc1-leaf2c.single-dc-l3ls-v2.io",
      "group": "",
      "labdir": "/home/matt/labs/avd_clab/single-dc-l3ls/clab-single-dc-l3ls-v2/dc1-leaf2c",
      "kind": "arista_ceos",
      "image": "ceos:4.35.0F",
      "mgmt-net": "",
      "mgmt-intf": "Management0",
      "mgmt-ipv4-address": "172.16.100.107",
      "mgmt-ipv4-prefix-length": 24,
      "mgmt-ipv6-address": "fd00:100:100::5",
      "mgmt-ipv6-prefix-length": 64,
      "mac-address": "00:1c:73:01:88:19",
      "labels": {
        "clab-mgmt-net-bridge": "br-ba55097e2c0c",
        "clab-node-group": "",
        "clab-node-kind": "arista_ceos",
        "clab-node-lab-dir": "/home/matt/labs/avd_clab/single-dc-l3ls/clab-single-dc-l3ls-v2/dc1-leaf2c",
        "clab-node-longname": "clab-single-dc-l3ls-v2-dc1-leaf2c",
        "clab-node-name": "dc1-leaf2c",
        "clab-node-type": "",
        "clab-owner": "matt",
        "clab-topo-file": "/home/matt/labs/avd_clab/single-dc-l3ls/l3ls.clab.yml",
        "containerlab": "single-dc-l3ls-v2"
      },
      "port-bindings": [
      ]
    },
    "dc1-spine1": {
      "index": "6",
      "shortname": "dc1-spine1",
      "longname": "clab-single-dc-l3ls-v2-dc1-spine1",
      "fqdn": "dc1-spine1.single-dc-l3ls-v2.io",
      "group": "",
      "labdir": "/home/matt/labs/avd_clab/single-dc-l3ls/clab-single-dc-l3ls-v2/dc1-spine1",
      "kind": "arista_ceos",
      "image": "ceos:4.35.0F",
      "mgmt-net": "",
      "mgmt-intf": "Management0",
      "mgmt-ipv4-address": "172.16.100.100",
      "mgmt-ipv4-prefix-length": 24,
      "mgmt-ipv6-address": "fd00:100:100::4",
      "mgmt-ipv6-prefix-length": 64,
      "mac-address": "00:1c:73:1f:65:16",
      "labels": {
        "clab-mgmt-net-bridge": "br-ba55097e2c0c",
        "clab-node-group": "",
        "clab-node-kind": "arista_ceos",
        "clab-node-lab-dir": "/home/matt/labs/avd_clab/single-dc-l3ls/clab-single-dc-l3ls-v2/dc1-spine1",
        "clab-node-longname": "clab-single-dc-l3ls-v2-dc1-spine1",
        "clab-node-name": "dc1-spine1",
        "clab-node-type": "",
        "clab-owner": "matt",
        "clab-topo-file": "/home/matt/labs/avd_clab/single-dc-l3ls/l3ls.clab.yml",
        "containerlab": "single-dc-l3ls-v2"
      },
      "port-bindings": [
      ]
    },
    "dc1-spine2": {
      "index": "7",
      "shortname": "dc1-spine2",
      "longname": "clab-single-dc-l3ls-v2-dc1-spine2",
      "fqdn": "dc1-spine2.single-dc-l3ls-v2.io",
      "group": "",
      "labdir": "/home/matt/labs/avd_clab/single-dc-l3ls/clab-single-dc-l3ls-v2/dc1-spine2",
      "kind": "arista_ceos",
      "image": "ceos:4.35.0F",
      "mgmt-net": "",
      "mgmt-intf": "Management0",
      "mgmt-ipv4-address": "172.16.100.101",
      "mgmt-ipv4-prefix-length": 24,
      "mgmt-ipv6-address": "fd00:100:100::9",
      "mgmt-ipv6-prefix-length": 64,
      "mac-address": "00:1c:73:19:67:5d",
      "labels": {
        "clab-mgmt-net-bridge": "br-ba55097e2c0c",
        "clab-node-group": "",
        "clab-node-kind": "arista_ceos",
        "clab-node-lab-dir": "/home/matt/labs/avd_clab/single-dc-l3ls/clab-single-dc-l3ls-v2/dc1-spine2",
        "clab-node-longname": "clab-single-dc-l3ls-v2-dc1-spine2",
        "clab-node-name": "dc1-spine2",
        "clab-node-type": "",
        "clab-owner": "matt",
        "clab-topo-file": "/home/matt/labs/avd_clab/single-dc-l3ls/l3ls.clab.yml",
        "containerlab": "single-dc-l3ls-v2"
      },
      "port-bindings": [
      ]
    },
    "server01": {
      "index": "8",
      "shortname": "server01",
      "longname": "clab-single-dc-l3ls-v2-server01",
      "fqdn": "server01.single-dc-l3ls-v2.io",
      "group": "",
      "labdir": "/home/matt/labs/avd_clab/single-dc-l3ls/clab-single-dc-l3ls-v2/server01",
      "kind": "linux",
      "image": "ghcr.io/hellt/network-multitool:latest",
      "mgmt-net": "",
      "mgmt-intf": "",
      "mgmt-ipv4-address": "172.16.100.3",
      "mgmt-ipv4-prefix-length": 24,
      "mgmt-ipv6-address": "fd00:100:100::b",
      "mgmt-ipv6-prefix-length": 64,
      "mac-address": "",
      "labels": {
        "clab-mgmt-net-bridge": "br-ba55097e2c0c",
        "clab-node-group": "",
        "clab-node-kind": "linux",
        "clab-node-lab-dir": "/home/matt/labs/avd_clab/single-dc-l3ls/clab-single-dc-l3ls-v2/server01",
        "clab-node-longname": "clab-single-dc-l3ls-v2-server01",
        "clab-node-name": "server01",
        "clab-node-type": "",
        "clab-owner": "matt",
        "clab-topo-file": "/home/matt/labs/avd_clab/single-dc-l3ls/l3ls.clab.yml",
        "containerlab": "single-dc-l3ls-v2"
      },
      "port-bindings": [
        {
          "host-ip": "",
          "host-port": 0,
          "port": 443,
          "protocol": "tcp"
        },
        {
          "host-ip": "",
          "host-port": 0,
          "port": 80,
          "protocol": "tcp"
        }
      ]
    },
    "server02": {
      "index": "9",
      "shortname": "server02",
      "longname": "clab-single-dc-l3ls-v2-server02",
      "fqdn": "server02.single-dc-l3ls-v2.io",
      "group": "",
      "labdir": "/home/matt/labs/avd_clab/single-dc-l3ls/clab-single-dc-l3ls-v2/server02",
      "kind": "linux",
      "image": "ghcr.io/hellt/network-multitool:latest",
      "mgmt-net": "",
      "mgmt-intf": "",
      "mgmt-ipv4-address": "172.16.100.2",
      "mgmt-ipv4-prefix-length": 24,
      "mgmt-ipv6-address": "fd00:100:100::a",
      "mgmt-ipv6-prefix-length": 64,
      "mac-address": "",
      "labels": {
        "clab-mgmt-net-bridge": "br-ba55097e2c0c",
        "clab-node-group": "",
        "clab-node-kind": "linux",
        "clab-node-lab-dir": "/home/matt/labs/avd_clab/single-dc-l3ls/clab-single-dc-l3ls-v2/server02",
        "clab-node-longname": "clab-single-dc-l3ls-v2-server02",
        "clab-node-name": "server02",
        "clab-node-type": "",
        "clab-owner": "matt",
        "clab-topo-file": "/home/matt/labs/avd_clab/single-dc-l3ls/l3ls.clab.yml",
        "containerlab": "single-dc-l3ls-v2"
      },
      "port-bindings": [
        {
          "host-ip": "",
          "host-port": 0,
          "port": 443,
          "protocol": "tcp"
        },
        {
          "host-ip": "",
          "host-port": 0,
          "port": 80,
          "protocol": "tcp"
        }
      ]
    }
  },
  "links": [
    {
      "endpoints": {
        "a": {
          "node": "dc1-spine1",
          "interface": "eth1",
          "mac": "aa:c1:ab:a9:e6:ba",
          "peer": "z"
        },
        "z": {
          "node": "dc1-leaf1a",
          "interface": "eth1",
          "mac": "aa:c1:ab:aa:e2:30",
          "peer": "a"
        }
      }
    },
    {
      "endpoints": {
        "a": {
          "node": "dc1-spine1",
          "interface": "eth2",
          "mac": "aa:c1:ab:de:f5:0f",
          "peer": "z"
        },
        "z": {
          "node": "dc1-leaf1b",
          "interface": "eth1",
          "mac": "aa:c1:ab:d6:12:b2",
          "peer": "a"
        }
      }
    },
    {
      "endpoints": {
        "a": {
          "node": "dc1-spine1",
          "interface": "eth3",
          "mac": "aa:c1:ab:6b:66:13",
          "peer": "z"
        },
        "z": {
          "node": "dc1-leaf2a",
          "interface": "eth1",
          "mac": "aa:c1:ab:b4:fe:88",
          "peer": "a"
        }
      }
    },
    {
      "endpoints": {
        "a": {
          "node": "dc1-spine1",
          "interface": "eth4",
          "mac": "aa:c1:ab:87:d8:60",
          "peer": "z"
        },
        "z": {
          "node": "dc1-leaf2b",
          "interface": "eth1",
          "mac": "aa:c1:ab:bb:50:b2",
          "peer": "a"
        }
      }
    },
    {
      "endpoints": {
        "a": {
          "node": "dc1-spine2",
          "interface": "eth1",
          "mac": "aa:c1:ab:67:62:33",
          "peer": "z"
        },
        "z": {
          "node": "dc1-leaf1a",
          "interface": "eth2",
          "mac": "aa:c1:ab:6b:5d:9e",
          "peer": "a"
        }
      }
    },
    {
      "endpoints": {
        "a": {
          "node": "dc1-spine2",
          "interface": "eth2",
          "mac": "aa:c1:ab:2a:c3:a0",
          "peer": "z"
        },
        "z": {
          "node": "dc1-leaf1b",
          "interface": "eth2",
          "mac": "aa:c1:ab:62:07:c9",
          "peer": "a"
        }
      }
    },
    {
      "endpoints": {
        "a": {
          "node": "dc1-spine2",
          "interface": "eth3",
          "mac": "aa:c1:ab:6a:fc:fb",
          "peer": "z"
        },
        "z": {
          "node": "dc1-leaf2a",
          "interface": "eth2",
          "mac": "aa:c1:ab:57:67:10",
          "peer": "a"
        }
      }
    },
    {
      "endpoints": {
        "a": {
          "node": "dc1-spine2",
          "interface": "eth4",
          "mac": "aa:c1:ab:f5:57:07",
          "peer": "z"
        },
        "z": {
          "node": "dc1-leaf2b",
          "interface": "eth2",
          "mac": "aa:c1:ab:2d:01:fb",
          "peer": "a"
        }
      }
    },
    {
      "endpoints": {
        "a": {
          "node": "dc1-leaf1a",
          "interface": "eth3",
          "mac": "aa:c1:ab:8b:7a:76",
          "peer": "z"
        },
        "z": {
          "node": "dc1-leaf1b",
          "interface": "eth3",
          "mac": "aa:c1:ab:2d:4f:30",
          "peer": "a"
        }
      }
    },
    {
      "endpoints": {
        "a": {
          "node": "dc1-leaf1a",
          "interface": "eth4",
          "mac": "aa:c1:ab:0f:25:cd",
          "peer": "z"
        },
        "z": {
          "node": "dc1-leaf1b",
          "interface": "eth4",
          "mac": "aa:c1:ab:9d:ee:d0",
          "peer": "a"
        }
      }
    },
    {
      "endpoints": {
        "a": {
          "node": "dc1-leaf2a",
          "interface": "eth3",
          "mac": "aa:c1:ab:5e:fc:01",
          "peer": "z"
        },
        "z": {
          "node": "dc1-leaf2b",
          "interface": "eth3",
          "mac": "aa:c1:ab:b6:d6:b8",
          "peer": "a"
        }
      }
    },
    {
      "endpoints": {
        "a": {
          "node": "dc1-leaf2a",
          "interface": "eth4",
          "mac": "aa:c1:ab:bc:b0:4a",
          "peer": "z"
        },
        "z": {
          "node": "dc1-leaf2b",
          "interface": "eth4",
          "mac": "aa:c1:ab:03:f1:83",
          "peer": "a"
        }
      }
    },
    {
      "endpoints": {
        "a": {
          "node": "dc1-leaf1c",
          "interface": "eth1",
          "mac": "aa:c1:ab:62:d5:5a",
          "peer": "z"
        },
        "z": {
          "node": "dc1-leaf1a",
          "interface": "eth8",
          "mac": "aa:c1:ab:a1:77:f1",
          "peer": "a"
        }
      }
    },
    {
      "endpoints": {
        "a": {
          "node": "dc1-leaf1c",
          "interface": "eth2",
          "mac": "aa:c1:ab:be:2c:0f",
          "peer": "z"
        },
        "z": {
          "node": "dc1-leaf1b",
          "interface": "eth8",
          "mac": "aa:c1:ab:e6:de:82",
          "peer": "a"
        }
      }
    },
    {
      "endpoints": {
        "a": {
          "node": "dc1-leaf2c",
          "interface": "eth1",
          "mac": "aa:c1:ab:63:bc:6f",
          "peer": "z"
        },
        "z": {
          "node": "dc1-leaf2a",
          "interface": "eth8",
          "mac": "aa:c1:ab:85:73:4a",
          "peer": "a"
        }
      }
    },
    {
      "endpoints": {
        "a": {
          "node": "dc1-leaf2c",
          "interface": "eth2",
          "mac": "aa:c1:ab:03:7d:a6",
          "peer": "z"
        },
        "z": {
          "node": "dc1-leaf2b",
          "interface": "eth8",
          "mac": "aa:c1:ab:3b:66:57",
          "peer": "a"
        }
      }
    },
    {
      "endpoints": {
        "a": {
          "node": "server01",
          "interface": "eth1",
          "mac": "aa:c1:ab:45:6d:67",
          "peer": "z"
        },
        "z": {
          "node": "dc1-leaf1c",
          "interface": "eth5",
          "mac": "aa:c1:ab:10:76:9a",
          "peer": "a"
        }
      }
    },
    {
      "endpoints": {
        "a": {
          "node": "server02",
          "interface": "eth1",
          "mac": "aa:c1:ab:80:57:e1",
          "peer": "z"
        },
        "z": {
          "node": "dc1-leaf2c",
          "interface": "eth5",
          "mac": "aa:c1:ab:d8:40:01",
          "peer": "a"
        }
      }
    }
  ]
}
